src/__init__.py
src/get_edition.py
news_scraper_pdf-1.1.4.dist-info/LICENCE
news_scraper_pdf-1.1.4.dist-info/METADATA
news_scraper_pdf-1.1.4.dist-info/WHEEL
news_scraper_pdf-1.1.4.dist-info/entry_points.txt
news_scraper_pdf-1.1.4.dist-info/top_level.txt
news_scraper_pdf-1.1.4.dist-info/RECORD
