Metadata-Version: 2.1
Name: news-scraper-pdf
Version: 1.1.4
Summary: Scrape news as PDF.
Author: pressomaniac
License: MIT
Classifier: Programming Language :: Python :: 3
Classifier: License :: OSI Approved :: MIT License
Classifier: Operating System :: OS Independent
License-File: LICENCE
Requires-Dist: dateparser==1.2.0
Requires-Dist: nc_py_api==0.14.0
Requires-Dist: pypdf==4.3.0
Requires-Dist: python-dotenv==1.0.1
Requires-Dist: Requests==2.32.3
Requires-Dist: selenium==4.22.0
Requires-Dist: thefuzz==0.22.1
